tempus_themes/autumn.py
tempus_themes/classic.py
tempus_themes/dawn.py
tempus_themes/day.py
tempus_themes/dusk.py
tempus_themes/fugit.py
tempus_themes/future.py
tempus_themes/night.py
tempus_themes/past.py
tempus_themes/rift.py
tempus_themes/spring.py
tempus_themes/summer.py
tempus_themes/tempest.py
tempus_themes/totus.py
tempus_themes/warp.py
tempus_themes/winter.py
tempus_themes-2.3.0.20220206.dist-info/LICENSE
tempus_themes-2.3.0.20220206.dist-info/METADATA
tempus_themes-2.3.0.20220206.dist-info/WHEEL
tempus_themes-2.3.0.20220206.dist-info/entry_points.txt
tempus_themes-2.3.0.20220206.dist-info/top_level.txt
tempus_themes-2.3.0.20220206.dist-info/RECORD
