Metadata-Version: 2.1
Name: tempus-themes
Version: 2.3.0.20220206
Summary: Accessible themes for Pygments
Home-page: https://gitlab.com/protesilaos/tempus-themes-generator
Author: Protesilaos Stavrou
Author-email: info@protesilaos.com
License: GPLv3+
Keywords: pygments,colorscheme
Platform: UNKNOWN
Classifier: Development Status :: 5 - Production/Stable
Classifier: Environment :: Plugins
Classifier: License :: OSI Approved :: GNU General Public License v3 or later (GPLv3+)
Classifier: Operating System :: OS Independent
Classifier: Programming Language :: Python
Classifier: Programming Language :: Python :: 3
Classifier: Topic :: Software Development :: Libraries :: Python Modules
Classifier: Topic :: Text Processing
License-File: LICENSE
Requires-Dist: pygments
